{
  "deploymentParams": {
    "poolAdmin": "0x009c4ba01488A15816093F96BA91210494E2C644",
    "poolEmergencyAdmin": "0x009c4ba01488A15816093F96BA91210494E2C644"
  },
  "protocolGlobalParams": {
    "ethUsdAggregator": "0x976B3D034E162d8bD72D6b9C989d545b839003b0",
    "marketId": "Xave Avalanche Market",
    "nativeTokenUsdAggregator": "0x976B3D034E162d8bD72D6b9C989d545b839003b0",
    "treasury": "0x235A2ac113014F9dcb8aBA6577F20290832dDEFd",
    "usdAddress": "0x10F7Fc1F91Ba351f9C629c5947AD69bD03C05b96",
    "wethAddress": "0x0000000000000000000000000000000000000000"
  },
  "tokens": [
    {
      "addr": "0xB97EF9Ef8734C71904D8002F8b6Bc66Dd9c48a6E",
      "borrowRate": 39000000000000000000000000,
      "chainLinkAggregator": {
        "aggregator": "0x29388a985C5904BFa13524f8c3Cb8bC10A02864C",
        "tokenReserve": "USDC"
      },
      "rateStrategy": {
        "baseVariableBorrowRate": 0,
        "name": "rateStrategyStableThree",
        "optimalUtilizationRate": 900000000000000000000000000,
        "stableRateSlope1": 0,
        "stableRateSlope2": 0,
        "tokenReserve": "USDC",
        "variableRateSlope1": 40000000000000000000000000,
        "variableRateSlope2": 600000000000000000000000000
      },
      "reserveConfig": {
        "aTokenImpl": "AToken",
        "baseLTVAsCollateral": 8000,
        "borrowingEnabled": true,
        "liquidationBonus": 10500,
        "liquidationThreshold": 9000,
        "reserveDecimals": 6,
        "reserveFactor": 1000,
        "stableBorrowRateEnabled": false,
        "tokenReserve": "USDC"
      }
    },
    {
      "addr": "0xC891EB4cbdEFf6e073e859e987815Ed1505c2ACD",
      "borrowRate": 35000000000000000000000000,
      "chainLinkAggregator": {
        "aggregator": "0xB9f4E777491bb848578B6FBa5c8A744A40d11128",
        "tokenReserve": "EURC"
      },
      "rateStrategy": {
        "baseVariableBorrowRate": 0,
        "name": "rateStrategyStableThree",
        "optimalUtilizationRate": 900000000000000000000000000,
        "stableRateSlope1": 0,
        "stableRateSlope2": 0,
        "tokenReserve": "EURC",
        "variableRateSlope1": 40000000000000000000000000,
        "variableRateSlope2": 600000000000000000000000000
      },
      "reserveConfig": {
        "aTokenImpl": "AToken",
        "baseLTVAsCollateral": 8000,
        "borrowingEnabled": false,
        "liquidationBonus": 10500,
        "liquidationThreshold": 9000,
        "reserveDecimals": 6,
        "reserveFactor": 1000,
        "stableBorrowRateEnabled": false,
        "tokenReserve": "EURC"
      }
    },
    {
      "addr": "0x228a48df6819CCc2eCa01e2192ebAFfFdAD56c19",
      "borrowRate": 35000000000000000000000000,
      "chainLinkAggregator": {
        "aggregator": "0x132b37560040268aA7c03F6C4f415F0eBf30A87b",
        "tokenReserve": "VCHF"
      },
      "rateStrategy": {
        "baseVariableBorrowRate": 0,
        "name": "rateStrategyStableThree",
        "optimalUtilizationRate": 900000000000000000000000000,
        "stableRateSlope1": 0,
        "stableRateSlope2": 0,
        "tokenReserve": "VCHF",
        "variableRateSlope1": 40000000000000000000000000,
        "variableRateSlope2": 600000000000000000000000000
      },
      "reserveConfig": {
        "aTokenImpl": "AToken",
        "baseLTVAsCollateral": 8000,
        "borrowingEnabled": false,
        "liquidationBonus": 10500,
        "liquidationThreshold": 9000,
        "reserveDecimals": 18,
        "reserveFactor": 1000,
        "stableBorrowRateEnabled": false,
        "tokenReserve": "VCHF"
      }
    },
    {
      "addr": "0x7678e162f38ec9ef2Bfd1d0aAF9fd93355E5Fa0b",
      "borrowRate": 35000000000000000000000000,
      "chainLinkAggregator": {
        "aggregator": "0xA7F333136d5cB3E26f95247Be2CCea4731ab6eAa",
        "tokenReserve": "VEUR"
      },
      "rateStrategy": {
        "baseVariableBorrowRate": 0,
        "name": "rateStrategyStableThree",
        "optimalUtilizationRate": 900000000000000000000000000,
        "stableRateSlope1": 0,
        "stableRateSlope2": 0,
        "tokenReserve": "VEUR",
        "variableRateSlope1": 40000000000000000000000000,
        "variableRateSlope2": 600000000000000000000000000
      },
      "reserveConfig": {
        "aTokenImpl": "AToken",
        "baseLTVAsCollateral": 8000,
        "borrowingEnabled": false,
        "liquidationBonus": 10500,
        "liquidationThreshold": 9000,
        "reserveDecimals": 18,
        "reserveFactor": 1000,
        "stableBorrowRateEnabled": false,
        "tokenReserve": "VEUR"
      }
    },
    {
      "addr": "0x7A1A919c033eBc0d9F23cBF2Aa41c24AEf826ca2",
      "borrowRate": 0,
      "chainLinkAggregator": {
        "aggregator": "0x94d81606Dca42D3680c0DFc1d93eeaF6C2D55f2d",
        "tokenReserve": "LP-EURC-USDC"
      },
      "rateStrategy": {
        "baseVariableBorrowRate": 0,
        "name": "rateStrategyStableThree",
        "optimalUtilizationRate": 900000000000000000000000000,
        "stableRateSlope1": 0,
        "stableRateSlope2": 0,
        "tokenReserve": "LP-EURC-USDC",
        "variableRateSlope1": 40000000000000000000000000,
        "variableRateSlope2": 600000000000000000000000000
      },
      "reserveConfig": {
        "aTokenImpl": "AToken",
        "baseLTVAsCollateral": 8000,
        "borrowingEnabled": false,
        "liquidationBonus": 10500,
        "liquidationThreshold": 8000,
        "reserveDecimals": 18,
        "reserveFactor": 1000,
        "stableBorrowRateEnabled": false,
        "tokenReserve": "LP-EURC-USDC"
      }
    },
    {
      "addr": "0x28F3a9e42667519c83cB090b5c4f6bd34e9F5569",
      "borrowRate": 0,
      "chainLinkAggregator": {
        "aggregator": "0x6360a8Adb883CA076e7F2c6d2fF37531A771e414",
        "tokenReserve": "LP-VEUR-USDC"
      },
      "rateStrategy": {
        "baseVariableBorrowRate": 0,
        "name": "rateStrategyStableThree",
        "optimalUtilizationRate": 900000000000000000000000000,
        "stableRateSlope1": 0,
        "stableRateSlope2": 0,
        "tokenReserve": "LP-VEUR-USDC",
        "variableRateSlope1": 40000000000000000000000000,
        "variableRateSlope2": 600000000000000000000000000
      },
      "reserveConfig": {
        "aTokenImpl": "AToken",
        "baseLTVAsCollateral": 8000,
        "borrowingEnabled": false,
        "liquidationBonus": 10500,
        "liquidationThreshold": 8000,
        "reserveDecimals": 18,
        "reserveFactor": 1000,
        "stableBorrowRateEnabled": false,
        "tokenReserve": "LP-VEUR-USDC"
      }
    },
    {
      "addr": "0x0099111Ed107BDF0B05162356aEe433514AaC440",
      "borrowRate": 0,
      "chainLinkAggregator": {
        "aggregator": "0xe5d80E9A857BF5cc73e40144cb28c8a401BdAe0c",
        "tokenReserve": "LP-VCHF-USDC"
      },
      "rateStrategy": {
        "baseVariableBorrowRate": 0,
        "name": "rateStrategyStableThree",
        "optimalUtilizationRate": 900000000000000000000000000,
        "stableRateSlope1": 0,
        "stableRateSlope2": 0,
        "tokenReserve": "LP-VCHF-USDC",
        "variableRateSlope1": 40000000000000000000000000,
        "variableRateSlope2": 600000000000000000000000000
      },
      "reserveConfig": {
        "aTokenImpl": "AToken",
        "baseLTVAsCollateral": 8000,
        "borrowingEnabled": false,
        "liquidationBonus": 10500,
        "liquidationThreshold": 8000,
        "reserveDecimals": 18,
        "reserveFactor": 1000,
        "stableBorrowRateEnabled": false,
        "tokenReserve": "LP-VCHF-USDC"
      }
    }
  ]
}
